pygrowth/__init__.py
pygrowth/general/__init__.py
pygrowth/general/hello.py
pygrowth-0.0.4.dist-info/METADATA
pygrowth-0.0.4.dist-info/RECORD
pygrowth-0.0.4.dist-info/WHEEL
pygrowth-0.0.4.dist-info/top_level.txt
