Metadata-Version: 2.1
Name: pygrowth
Version: 0.0.4
Summary: Python package for public data analyses from the GROWTH collaboratoin.
Home-page: https://github.com/growth-team/pygrowth
Author: GROWTH-team
Author-email: teruaki.enoto@gmail.com
Maintainer: Teru Enoto
Maintainer-email: teruaki.enoto@gmail.com
License: MIT
Platform: UNKNOWN
Requires-Dist: numpy
